<?xml version="1.0" encoding="utf-8"?>
<odoo>

    <!-- zetomart.person tree view -->
    <record id="zetomart_person_view_tree" model="ir.ui.view">
        <field name="name">zetomart.person.view.tree</field>
        <field name="model">zetomart.person</field>
        <field name="arch" type="xml">
            <tree>
                <field name="name"/>
                <field name="alamat"/>
                <field name="tgl_lahir"/>
            </tree>
        </field>
    </record>

    <!-- zetomart.person form view -->
    <record id="zetomart_person_view_form" model="ir.ui.view">
        <field name="name">zetomart.person.view.form</field>
        <field name="model">zetomart.person</field>
        <field name="arch" type="xml">
            <form string="Nama">
                <sheet>
                    <group name='nama' string='Nama'>
                        <field name="name"/>
                    </group>
                    <group name="data" string="Data">
                        <field name="alamat"/>
                        <field name="tgl_lahir"/>
                    </group>
                </sheet>
            </form>
        </field>
    </record>

</odoo>
